mdrender/__init__.py
mdrender/cli.py
mdrender-0.1.0.dist-info/licenses/LICENSE
mdrender-0.1.0.dist-info/METADATA
mdrender-0.1.0.dist-info/WHEEL
mdrender-0.1.0.dist-info/entry_points.txt
mdrender-0.1.0.dist-info/top_level.txt
mdrender-0.1.0.dist-info/RECORD
