Metadata-Version: 2.4
Name: mdrender
Version: 0.1.0
Summary: A streaming Markdown renderer for your terminal, great to render the output of LLM tools
Author-email: adiffpirate <adiffpirate@gmail.com>
License: MIT
Requires-Python: >=3.7
License-File: LICENSE
Requires-Dist: rich>=13.0.0
Dynamic: license-file
